[
  {
    "id": "269e0ea0-0a8d-4674-8f76-9236de0fee06",
    "title": "Third",
    "createdAt": "2024-04-26T19:16:03.807Z",
    "updatedAt": "2024-04-26T19:16:03.807Z",
    "prioritizedAt": "",
    "completed": false,
    "priority": false,
    "subTodos": []
  },
  {
    "id": "28667eda-486e-44ce-8051-20ee2367b4a2",
    "title": "Second",
    "createdAt": "2024-04-26T19:16:01.790Z",
    "updatedAt": "2024-04-26T19:16:01.790Z",
    "prioritizedAt": "",
    "completed": false,
    "priority": false,
    "subTodos": []
  },
  {
    "id": "71112a97-ea9d-48ad-a02c-d06a6a2da3a7",
    "title": "First",
    "createdAt": "2024-04-26T19:15:59.804Z",
    "updatedAt": "2024-04-26T19:15:59.804Z",
    "prioritizedAt": "",
    "completed": false,
    "priority": false,
    "subTodos": [
      {
        "id": "2db49065-43a8-404e-b611-8b390704bbb8",
        "title": "Sub first",
        "createdAt": "2024-04-26T19:16:10.220Z",
        "updatedAt": "2024-04-26T19:16:10.220Z",
        "prioritizedAt": "",
        "completed": false,
        "priority": false,
        "subTodos": [
          {
            "id": "137a810d-6fb1-489f-b0f8-fb6af9c59128",
            "title": "Sub second",
            "createdAt": "2024-04-26T19:16:15.970Z",
            "updatedAt": "2024-04-26T19:16:15.970Z",
            "prioritizedAt": "",
            "completed": false,
            "priority": false,
            "subTodos": []
          }
        ]
      }
    ]
  }
]